sammi/CITATION.rst
sammi/__init__.py
sammi/_version.py
sammi/cdf_attribute_manager.py
sammi/schema.py
sammi/data/README.rst
sammi/data/default_global_cdf_attrs_schema.yaml
sammi/data/default_variable_cdf_attrs_schema.yaml
sammi/data/imap_default_global_cdf_attrs.yaml
sammi/data/shared/default_global_cdf_attrs_schema.yaml
sammi/data/shared/default_variable_cdf_attrs_schema.yaml
sammi/tests/__init__.py
sammi/tests/test_cdf_attribute_manager.py
sammi/tests/test_schema.py
sammi/tests/shared/default_global_cdf_attrs_schema.yaml
sammi/tests/shared/default_variable_cdf_attrs_schema.yaml
sammi/tests/test_data/default_global_test_cdf_attrs.yaml
sammi/tests/test_data/imap_default_global_cdf_attrs.yaml
sammi/tests/test_data/imap_default_global_test_cdf_attrs.yaml
sammi/tests/test_data/imap_instrument1_global_cdf_attrs.yaml
sammi/tests/test_data/imap_instrument1_level1_variable_attrs.yaml
sammi/tests/test_data/imap_instrument2_global_cdf_attrs.yaml
sammi/tests/test_data/imap_instrument2_level2_variable_attrs.yaml
sammi/tests/test_data/imap_test_global.yaml
sammi/tests/test_data/imap_test_variable.yaml
sammi_cdf-0.1.0.dev0.dist-info/LICENSE.rst
sammi_cdf-0.1.0.dev0.dist-info/METADATA
sammi_cdf-0.1.0.dev0.dist-info/WHEEL
sammi_cdf-0.1.0.dev0.dist-info/top_level.txt
sammi_cdf-0.1.0.dev0.dist-info/RECORD
