Metadata-Version: 2.1
Name: sammi-cdf
Version: 0.1.0.dev0
Summary: A Python package to support metadata attriubte management for Space Weather data processing pipelines.
Author-email: Andrew Robbertz <a.robbertz@gmail.com>, IMAP SDC Developers <imap.sdc@lists.lasp.colorado.edu>
License: see licenses/LICENSE.md
Project-URL: Homepage, https://github.com/swxsoc/sammi
Keywords: sammi,nasa mission,space weather
Classifier: Development Status :: 3 - Alpha
Classifier: Natural Language :: English
Classifier: Operating System :: OS Independent
Classifier: Programming Language :: Python
Classifier: Programming Language :: Python :: 3.9
Classifier: Intended Audience :: Science/Research
Classifier: Topic :: Scientific/Engineering
Classifier: Topic :: Scientific/Engineering :: Physics
Requires-Python: >=3.9
License-File: LICENSE.rst
Requires-Dist: pyyaml>=5.3.1
Provides-Extra: dev
Requires-Dist: coverage>=5.0.3; extra == "dev"
Requires-Dist: pytest==8.0.0; extra == "dev"
Requires-Dist: pytest-astropy==0.11.0; extra == "dev"
Requires-Dist: pytest-cov==4.1.0; extra == "dev"
Requires-Dist: black==24.1.1; extra == "dev"
Requires-Dist: flake8==7.0.0; extra == "dev"
Requires-Dist: coverage[toml]==7.4.1; extra == "dev"
Provides-Extra: docs
Requires-Dist: sphinx==7.2.6; extra == "docs"
Requires-Dist: sphinx-automodapi==0.16.0; extra == "docs"
Requires-Dist: sphinx-copybutton==0.5.2; extra == "docs"
Provides-Extra: style
Requires-Dist: black==24.1.1; extra == "style"
Requires-Dist: flake8==7.0.0; extra == "style"
Requires-Dist: rstcheck==6.2.0; extra == "style"
Provides-Extra: test
Requires-Dist: pytest==8.0.0; extra == "test"
Requires-Dist: pytest-astropy==0.11.0; extra == "test"
Requires-Dist: pytest-cov==4.1.0; extra == "test"
Requires-Dist: coverage[toml]==7.4.1; extra == "test"
